tox_bindep/__init__.py
tox_bindep/hooks.py
tox_bindep-0.2.1.dist-info/LICENSE
tox_bindep-0.2.1.dist-info/METADATA
tox_bindep-0.2.1.dist-info/WHEEL
tox_bindep-0.2.1.dist-info/entry_points.txt
tox_bindep-0.2.1.dist-info/top_level.txt
tox_bindep-0.2.1.dist-info/RECORD
